treesap/NHPP.py
treesap/__init__.py
treesap/birthdeath.py
treesap/coalescent.py
treesap/common.py
treesap/dualbirth.py
treesap/transmission_neutral_coalescent.py
treesap/yule.py
treesap-1.0.10.dist-info/LICENSE.txt
treesap-1.0.10.dist-info/METADATA
treesap-1.0.10.dist-info/RECORD
treesap-1.0.10.dist-info/WHEEL
treesap-1.0.10.dist-info/top_level.txt
