Metadata-Version: 2.1
Name: treesap
Version: 1.0.10
Summary: TreeSAP: Tree SAmpling under Phylogenetic models
Home-page: https://github.com/niemasd/TreeSAP
Author: Niema Moshiri
Author-email: niemamoshiri@gmail.com
License: UNKNOWN
Project-URL: Source, https://github.com/niemasd/TreeSAP
Project-URL: Bug Reports, https://github.com/niemasd/TreeSAP/issues
Keywords: non homogeneous yule simulator
Platform: UNKNOWN
Classifier: Development Status :: 3 - Alpha
Classifier: Intended Audience :: Developers
Classifier: Topic :: Software Development :: Build Tools
Classifier: License :: OSI Approved :: GNU General Public License v3 or later (GPLv3+)
Classifier: Programming Language :: Python :: 3.4
Classifier: Programming Language :: Python :: 3.5
Classifier: Programming Language :: Python :: 3.6
Classifier: Programming Language :: Python :: 3.7
Provides-Extra: dev
Requires-Dist: numpy
Requires-Dist: scipy
Requires-Dist: treeswift
Provides-Extra: dev
Requires-Dist: check-manifest; extra == 'dev'
